call_seq
