Metadata-Version: 1.0
Name: call-seq
Version: 0.0.2
Summary: call sequence visualization
Home-page: https://github.com/ya790206/call_seq
Author: ya790206
Author-email: UNKNOWN
License: Apache License Version 2.0
Platform: any
